Workbook

Sheet Resumen
B2: GRABI M001 · Unit Economics del piloto
B3: Máquina expendedora 4 canales · pago Bre-B + QR firmado · Colombia · elaborado 2026-07-22
B5: INDICADORES CLAVE (se calculan solos) | D5: CÓMO LEERLO
B6: CAPEX total por máquina | C6: ='Supuestos'!C15 | D6: Inversión para dejar 1 máquina lista. Editable en 'Supuestos'.
B7: Margen de contribución por unidad (prom. ponderado) | C7: ='Productos'!E11 | D7: Precio − costo producto − comisión pago, ponderado por mezcla de ventas.
B8: Ticket promedio (precio venta ponderado) | C8: ='Productos'!C11 | D8: Cuánto paga en promedio el cliente por compra.
B9: Unidades vendidas / mes | C9: ='Modelo mensual'!C7 | D9: =ventas/día × días operativos (editable en 'Supuestos').
B10: Ingresos / mes | C10: ='Modelo mensual'!C8 | D10: Facturación bruta mensual de la máquina.
B11: Margen de contribución / mes | C11: ='Modelo mensual'!C9 | D11: Antes de restar costos operativos fijos.
B12: Utilidad neta / mes por máquina | C12: ='Modelo mensual'!C11 | D12: Después de reabastecimiento, renta, software y comisiones.
B13: PAYBACK (meses para recuperar CAPEX) | C13: ='Modelo mensual'!C13 | D13: CAPEX ÷ utilidad mensual. Menor = mejor. Umbral go/no-go abajo.
B15: VEREDICTO GO / NO-GO
B16: Umbral de payback aceptable (meses) — EDITABLE | C16: 12 | D16: Regla sugerida: piloto sano si recupera la inversión en ≤ 12 meses (ajústalo a tu apetito).
B17: Resultado automático | C17: =IF('Modelo mensual'!C11<=0,"NO-GO · utilidad mensual ≤ 0",IF('Modelo mensual'!C13<=C16,"GO · payback dentro del umbral","REVISAR · payback supera el umbral"))
B19: Cómo usar: cambia SOLO las celdas amarillas (hoja 'Supuestos' y 'Productos'). Todo lo demás se recalcula. Los costos de producto son estimados de fuentes públicas 2026 (ver hoja 'Fuentes'); confírmalos en tienda antes de decidir.

Sheet Supuestos
B2: SUPUESTOS EDITABLES · celdas amarillas = llenar con dato real
B4: A) CAPEX — inversión por máquina | D4: Nota / fuente del dato
B5: ESP32 (MCU) | C5: 25000 | D5: Dept. 03 electrónica — reemplazar con precio real de compra
B6: Lector QR GM65 (u similar) | C6: 60000 | D6: Dept. 03 — el ítem más caro de la electrónica
B7: RTC DS3231 (reloj para expiración offline) | C7: 8000 | D7: Dept. 03
B8: Fuente de alimentación | C8: 25000 | D8: Dept. 03
B9: Drivers de motor + espiral (electrónica) | C9: 40000 | D9: Dept. 03 — 4 canales
B10: Sensor de caída (confirmación dispensado) | C10: 15000 | D10: Dept. 03
B11: Pantalla / cableado / varios electrónica | C11: 20000 | D11: Dept. 03
B12: Estructura mecánica (parte del amigo) | C12: 300000 | D12: Dept. 01 — COTIZAR con tu socio; placeholder
B13: Instalación / anclaje en punto | C13: 50000 | D13: Dept. 05 operaciones
B14: Otros (imprevistos, empaques, etiquetas) | C14: 30000 | D14: Colchón; ajustar
B15: TOTAL CAPEX por máquina | C15: =SUM(C5:C14) | D15: Se usa en Resumen y Payback.
B17: B) COSTOS OPERATIVOS mensuales (fijos por máquina) | D17: Nota
B18: Reabastecimiento (transporte + tiempo) | C18: 60000 | D18: Dept. 05 — viajes de surtido al mes
B19: Renta / comisión del espacio | C19: 0 | D19: Dept. 05/06 — 0 si es comodato; poner $ o usar % abajo
B20: Prorrateo software (VPS + dominio) | C20: 15000 | D20: Dept. 02 — se reparte entre nº de máquinas
B21: Mantenimiento / mermas estimadas | C21: 20000 | D21: Colchón operativo
B22: TOTAL OPEX mensual | C22: =SUM(C18:C21)
B24: C) PAGOS Y VENTAS | D24: Nota
B25: Comisión de pago (% sobre venta) | C25: 0 | D25: Bre-B directo ≈ 0%. Si usas agregador (Mono/Cobre), pon su % aquí.
B26: Ventas por día (unidades, toda la máquina) | C26: 15 | D26: Dept. 05 — supuesto clave. Prueba 5 / 15 / 30 y mira el payback.
B27: Días operativos por mes | C27: 30 | D27: 30 = todos los días; baja si el punto cierra fines de semana.

Sheet Productos
B2: PRODUCTOS · Canasta económica v2 (4 canales) · costos y precios EDITABLES
B4: Slot / Producto | C4: Precio venta | D4: Costo producto | E4: Margen unit. (neto de comisión) | F4: % mezcla de ventas | G4: Margen %
B5: 1 · Platanitos / Yupi (indiv. 22–25 g) | C5: 2000 | D5: 1000 | E5: =C5-D5-C5*Supuestos!C25 | F5: 0.3 | G5: =IF(C5=0,0,E5/C5)
B6: 2 · Maní individual (40–50 g) | C6: 2000 | D6: 1400 | E6: =C6-D6-C6*Supuestos!C25 | F6: 0.2 | G6: =IF(C6=0,0,E6/C6)
B7: 3 · Agua 600 ml | C7: 2500 | D7: 800 | E7: =C7-D7-C7*Supuestos!C25 | F7: 0.3 | G7: =IF(C7=0,0,E7/C7)
B8: 4 · Speed Max 400 ml (energizante) | C8: 2500 | D8: 1900 | E8: =C8-D8-C8*Supuestos!C25 | F8: 0.2 | G8: =IF(C8=0,0,E8/C8)
B9: Suma mezcla (debe dar 100%) | F9: =SUM(F5:F8)
B11: PROMEDIO PONDERADO (por mezcla) | C11: =SUMPRODUCT(C5:C8,F5:F8)/SUM(F5:F8) | D11: ← ticket prom. | E11: =SUMPRODUCT(E5:E8,F5:F8)/SUM(F5:F8) | G11: =IF(C11=0,0,E11/C11)
B13: Nota: 'Margen unit.' resta la comisión de pago definida en Supuestos (Bre-B directo = 0%). Costos = estimado de fuentes públicas 2026 (hoja 'Fuentes'). D1 no vende porción individual pequeña: confirma en tienda el costo real de cada presentación de vending.

Sheet Modelo mensual
B2: MODELO MENSUAL — 1 máquina (todo calculado)
B4: Concepto | C4: Valor | D4: Fórmula / origen
B5: Ventas por día (unidades) | C5: =Supuestos!C26 | D5: Supuesto (editable)
B6: Días operativos / mes | C6: =Supuestos!C27 | D6: Supuesto (editable)
B7: Unidades vendidas / mes | C7: =C5*C6 | D7: ventas/día × días
B8: Ingresos / mes | C8: =C7*Productos!C11 | D8: unidades × ticket promedio
B9: Margen de contribución / mes | C9: =C7*Productos!E11 | D9: unidades × margen unit. ponderado
B10: (−) Costos operativos / mes | C10: =-Supuestos!C22 | D10: Total OPEX (Supuestos)
B11: =UTILIDAD NETA / mes por máquina | C11: =C9+C10 | D11: Margen de contribución − OPEX
B12: Utilidad neta / año | C12: =C11*12
B13: PAYBACK (meses) | C13: =IF(C11<=0,"n/a (sin utilidad)",Supuestos!C15/C11) | D13: CAPEX ÷ utilidad neta mensual

Sheet Escenarios
B2: ESCENARIOS — escalado y sensibilidad
B4: A) Flota de máquinas (misma economía por máquina)
B5: Concepto | C5: 1 máquina | D5: 5 máquinas | E5: 20 máquinas
B6: Nº máquinas | C6: 1 | D6: 5 | E6: 20
B7: CAPEX total | C7: =Supuestos!C15*1 | D7: =Supuestos!C15*5 | E7: =Supuestos!C15*20
B8: Utilidad neta / mes | C8: ='Modelo mensual'!C11*1 | D8: ='Modelo mensual'!C11*5 | E8: ='Modelo mensual'!C11*20
B9: Utilidad neta / año | C9: ='Modelo mensual'!C11*12*1 | D9: ='Modelo mensual'!C11*12*5 | E9: ='Modelo mensual'!C11*12*20
B10: Payback (meses) | C10: =IF('Modelo mensual'!C11<=0,"n/a",C7/C8) | D10: =IF('Modelo mensual'!C11<=0,"n/a",D7/D8) | E10: =IF('Modelo mensual'!C11<=0,"n/a",E7/E8)
B11: Nota: el payback por máquina no cambia con la flota (misma economía). Lo que cambia al escalar es la utilidad absoluta y el CAPEX total. Costos que bajan por volumen (compra de producto, electrónica) y costos que suben (logística, soporte) deben ajustarse manualmente en 'Supuestos' para cada escenario real.
B13: B) Sensibilidad a ventas/día (1 máquina)
B14: Ventas/día | C14: Utilidad neta/mes | D14: Payback (meses)
B15: 5 u/día | C15: =5*Supuestos!C27*Productos!E11-Supuestos!C22 | D15: =IF((5*Supuestos!C27*Productos!E11-Supuestos!C22)<=0,"n/a",Supuestos!C15/(5*Supuestos!C27*Productos!E11-Supuestos!C22))
B16: 10 u/día | C16: =10*Supuestos!C27*Productos!E11-Supuestos!C22 | D16: =IF((10*Supuestos!C27*Productos!E11-Supuestos!C22)<=0,"n/a",Supuestos!C15/(10*Supuestos!C27*Productos!E11-Supuestos!C22))
B17: 15 u/día | C17: =15*Supuestos!C27*Productos!E11-Supuestos!C22 | D17: =IF((15*Supuestos!C27*Productos!E11-Supuestos!C22)<=0,"n/a",Supuestos!C15/(15*Supuestos!C27*Productos!E11-Supuestos!C22))
B18: 20 u/día | C18: =20*Supuestos!C27*Productos!E11-Supuestos!C22 | D18: =IF((20*Supuestos!C27*Productos!E11-Supuestos!C22)<=0,"n/a",Supuestos!C15/(20*Supuestos!C27*Productos!E11-Supuestos!C22))
B19: 30 u/día | C19: =30*Supuestos!C27*Productos!E11-Supuestos!C22 | D19: =IF((30*Supuestos!C27*Productos!E11-Supuestos!C22)<=0,"n/a",Supuestos!C15/(30*Supuestos!C27*Productos!E11-Supuestos!C22))
B20: 40 u/día | C20: =40*Supuestos!C27*Productos!E11-Supuestos!C22 | D20: =IF((40*Supuestos!C27*Productos!E11-Supuestos!C22)<=0,"n/a",Supuestos!C15/(40*Supuestos!C27*Productos!E11-Supuestos!C22))

Sheet Fuentes
B2: FUENTES DE PRECIOS — investigación 2026-07-22
B3: Regla: D1 es hard-discount, NO vende al por mayor → su precio de góndola ES tu costo. D1 casi no maneja porción individual pequeña (ideal para vending): esos costos vienen de retail/mayorista y hay que CONFIRMARLOS en tienda. Retail de conveniencia (OXXO) sirve como techo de precio de venta.
B5: Producto / Marca | C5: Tamaño | D5: Precio COP | E5: Tienda / Tipo | F5: Fuente (URL)
B6: Agua Omi con gas (D1) | C6: 600 ml | D6: $890 | E6: D1 · góndola=costo | F6: https://losprecios.co/d1_t1/bebidas/aguas_s18
B7: Agua Omi botella (D1) | C7: 1.000 ml | D7: $950 | E7: D1 · góndola=costo | F7: https://losprecios.co/d1_t1/bebidas/aguas_s18
B8: Agua Omi sin gas 600 ml (D1) | C8: 600 ml | D8: NO listada | E8: D1 · CONFIRMAR EN TIENDA | F8: https://losprecios.co/d1_t1/bebidas/aguas_s18
B9: Agua Cristal sin gas | C9: 600 ml | D9: $1.650 | E9: Megatiendas · retail | F9: https://www.megatiendas.co/agua-cristal-sin-gas-x-600-ml-7702090022711/p
B10: Agua Cristal (paca x24) | C10: 600 ml c/u | D10: ~$630/u | E10: Éxito · mayorista/paca | F10: https://www.exito.com/agua-ahorra-pack-pet-845228/p
B11: Agua Cristal | C11: 600 ml | D11: $2.200 | E11: OXXO · conveniencia (techo) | F11: https://colombia.oxxodomicilios.com/product-details/agua-purificada-cristal-600ml/01H1Y71ZTVND8EWVXHS05EHMWQ
B12: Papas Kythos (D1) | C12: 115 g | D12: $3.400 | E12: D1 · góndola=costo (bolsa grande) | F12: https://losprecios.co/d1_t1/dulces-y-pasabocas/paquetes_s45
B13: Platanitos Plataitos (D1) | C13: 80 g | D13: $4.250 | E13: D1 · góndola=costo | F13: https://losprecios.co/d1_t1/dulces-y-pasabocas/paquetes_s45
B14: Yupi Clásica (pack x12) | C14: 22 g c/u | D14: ~$975/u | E14: Múcura · mayorista | F14: https://mucura.co/bogota/marca/yupi
B15: Margarita Papas Natural | C15: individual | D15: $2.010 | E15: Rappi · retail | F15: https://www.rappi.com.co/p/margarita-papas-fritas-natural-101993
B16: Platanitos indiv. pequeño | C16: ~25-30 g | D16: NO confirmado | E16: CONFIRMAR EN TIENDA | F16: (catálogo Comestibles Ricos sin precio unitario)
... B25: Chocolatina Jet (D1) | C25: 22 g | D25: $2.000 | E25: D1 · góndola=costo | F25: https://losprecios.co/d1_t1/dulces-y-pasabocas/chocolatinas_s47
B27: Rojo = dato NO encontrado / a confirmar por Daniel en tienda física. Mercamío (Cali) no fue consultable por Rappi (SPA con login); usar app logueada o visita presencial para precios exactos.
